pyvmcon/__init__.py
pyvmcon/exceptions.py
pyvmcon/problem.py
pyvmcon/vmcon.py
pyvmcon-2.4.1.dist-info/licenses/LICENSE
pyvmcon-2.4.1.dist-info/METADATA
pyvmcon-2.4.1.dist-info/WHEEL
pyvmcon-2.4.1.dist-info/top_level.txt
pyvmcon-2.4.1.dist-info/RECORD
