Metadata-Version: 2.4
Name: PyVMCON
Version: 2.4.1
Summary: Python implementation of the VMCON non-linear constrained optimiser.
Author-email: Timothy Nunn <timothy.nunn@ukaea.uk>
License: MIT License
Project-URL: Documentation, https://ukaea.github.io/PyVMCON/
Project-URL: Source, https://github.com/ukaea/PyVMCON
Keywords: vmcon,optimisation,non-linear constrained optimisation
Classifier: Intended Audience :: Science/Research
Classifier: License :: OSI Approved :: MIT License
Classifier: Topic :: Scientific/Engineering
Classifier: Programming Language :: Python :: 3
Requires-Python: >=3.10
License-File: LICENSE
Requires-Dist: numpy>=1.24
Requires-Dist: cvxpy>=1.6
Provides-Extra: docs
Requires-Dist: Sphinx>=6.1; extra == "docs"
Requires-Dist: sphinxcontrib-mermaid>=0.9; extra == "docs"
Requires-Dist: nbsphinx>=0.9; extra == "docs"
Requires-Dist: ipython; extra == "docs"
Requires-Dist: ipykernel; extra == "docs"
Requires-Dist: nbformat>=4.2; extra == "docs"
Dynamic: license-file
